iguana/__init__.py
iguana/iguana.py
iguana-0.1.7.dist-info/LICENSE
iguana-0.1.7.dist-info/METADATA
iguana-0.1.7.dist-info/WHEEL
iguana-0.1.7.dist-info/entry_points.txt
iguana-0.1.7.dist-info/top_level.txt
iguana-0.1.7.dist-info/RECORD
