Metadata-Version: 2.1
Name: iguana
Version: 0.1.7
Summary: A network scanning tool for Kali Linux
Home-page: https://pypi.org/project/iguana/
Author: Uveis Smajli
Author-email: smajliuveis@yahoo.com
Classifier: Programming Language :: Python :: 3
Classifier: License :: OSI Approved :: MIT License
Classifier: Operating System :: OS Independent
Requires-Python: >=3.6
License-File: LICENSE
Requires-Dist: dnspython
Requires-Dist: scapy
